httpout_session/__init__.py
httpout_session-0.0.0.dist-info/LICENSE
httpout_session-0.0.0.dist-info/METADATA
httpout_session-0.0.0.dist-info/WHEEL
httpout_session-0.0.0.dist-info/top_level.txt
httpout_session-0.0.0.dist-info/RECORD
