Metadata-Version: 2.1
Name: httpout-session
Version: 0.0.0
Summary: A simple, file-based session middleware for httpout.
Author-email: nggit <contact@anggit.com>
License: MIT License
Project-URL: Homepage, https://github.com/nggit/httpout-session
Project-URL: Source, https://github.com/nggit/httpout-session
Project-URL: Funding, https://github.com/sponsors/nggit
Classifier: Development Status :: 4 - Beta
Classifier: Intended Audience :: Developers
Classifier: License :: OSI Approved :: MIT License
Classifier: Operating System :: OS Independent
Classifier: Topic :: Software Development :: Libraries :: Application Frameworks
Requires-Python: >=3.7
License-File: LICENSE
Requires-Dist: httpout
Requires-Dist: tremolo-session
